ccloud_cli_api/__init__.py
ccloud_cli_api/aws_secret.py
ccloud_cli_api/ccloud_cli_api.py
ccloud_cli_api/tools.py
ccloud_cli_api-0.1.0.dist-info/LICENSE
ccloud_cli_api-0.1.0.dist-info/WHEEL
ccloud_cli_api-0.1.0.dist-info/METADATA
ccloud_cli_api-0.1.0.dist-info/RECORD
